[
    {
        "roll": 2,
        "name": "Ranit",
        "age": 21,
        "class": "12",
        "marks": 89.0,
        "gender": "Male"
    },
    {
        "roll": 1,
        "name": "Abantika",
        "age": 20,
        "class": "5",
        "marks": 67.0,
        "gender": "Female"
    },
    {
        "roll": 3,
        "name": "Anu",
        "age": 20,
        "class": "10",
        "gender": "Female",
        "marks": 93.0
    },
    {
        "roll": 4,
        "name": "Ankita",
        "age": 20,
        "class": "12",
        "gender": "Female",
        "marks": 89.0
    },
    {
        "roll": 6,
        "name": "Lisa",
        "age": 22,
        "class": "12",
        "gender": "Female",
        "marks": 94.0
    },
    {
        "roll": 7,
        "name": "Prabir",
        "age": 21,
        "class": "12",
        "gender": "Male",
        "marks": 93.0
    },
    {
        "roll": 5,
        "name": "Priya",
        "age": 21,
        "class": "12",
        "gender": "Female",
        "marks": 86.0
    }
]